Metadata-Version: 1.0
Name: matrix-product
Version: 1.3
Summary: Matrix Multiplications
Home-page: UNKNOWN
Author: Hakan ATESLI
Author-email: hakanatesli9000@gmail.com
License: UNKNOWN
Platform: UNKNOWN
